LICENSE
MANIFEST.in
README.md
requirements.txt
setup.py
bin/build-pathway-database.py
bin/download-kegg-pathways.sh
bin/get-identifier-mapping-from-gff.py
bin/get-kos-from-pykofamsearch.py
bin/profile-pathway-coverage.py
kegg_pathway_profiler/__init__.py
kegg_pathway_profiler/enrichment.py
kegg_pathway_profiler/parse.py
kegg_pathway_profiler/pathways.py
kegg_pathway_profiler/utils.py
kegg_pathway_profiler.egg-info/PKG-INFO
kegg_pathway_profiler.egg-info/SOURCES.txt
kegg_pathway_profiler.egg-info/dependency_links.txt
kegg_pathway_profiler.egg-info/requires.txt
kegg_pathway_profiler.egg-info/top_level.txt