Metadata-Version: 2.4
Name: kegg_pathway_profiler
Version: 2025.12.5
Summary: KEGG Pathway Profiler
Home-page: https://github.com/jolespin/kegg_pathway_profiler
Author: Josh L. Espinoza
License: Apache 2.0
Requires-Python: >=3.6
License-File: LICENSE
Requires-Dist: networkx>=3.0
Requires-Dist: numpy>=1.9
Requires-Dist: scipy>=1.11
Requires-Dist: pandas>=1.0
Requires-Dist: tqdm
Requires-Dist: pyexeggutor>=2025.12.5
Dynamic: author
Dynamic: description
Dynamic: description-content-type
Dynamic: home-page
Dynamic: license
Dynamic: license-file
Dynamic: requires-dist
Dynamic: requires-python
Dynamic: summary
